[
  {
    "id": 1,
    "symbol": "786",
    "fullName": "786 Investments Limited",
    "icon": "test.svg"
  },
  {
    "id": 3,
    "symbol": "AABS",
    "fullName": "Al-Abbas Sugar Mills Limited",
    "icon": "test.svg"
  },
  {
    "id": 4,
    "symbol": "AAL",
    "fullName": "Agro Allianz Limited(DEF)",
    "icon": "test.svg"
  },
  {
    "id": 5,
    "symbol": "AASM",
    "fullName": "Al-Abid Silk Mills Limited(DEF)",
    "icon": "test.svg"
  },
  {
    "id": 6,
    "symbol": "AATM",
    "fullName": "Ali Asghar Textile Mills Limited",
    "icon": "test.svg"
  },
  {
    "id": 7,
    "symbol": "ABL",
    "fullName": "Allied Bank Limited",
    "icon": "test.svg"
  },
  {
    "id": 8,
    "symbol": "ABOT",
    "fullName": "Abbott Laboratories (Pakistan) Limited",
    "icon": "test.svg"
  },
  {
    "id": 9,
    "symbol": "ABSON",
    "fullName": "Abson Industries Limited(DEF)",
    "icon": "test.svg"
  },
  {
    "id": 10,
    "symbol": "ACIETF",
    "fullName": "Alfalah Consumer Index (ETF)(XD)",
    "icon": "test.svg"
  },
  {
    "id": 11,
    "symbol": "ACPL",
    "fullName": "Attock Cement Pakistan Limited",
    "icon": "test.svg"
  },
  {
    "id": 12,
    "symbol": "ADAMS",
    "fullName": "Adam Sugar Mills Limited",
    "icon": "test.svg"
  },
  {
    "id": 13,
    "symbol": "ADMM",
    "fullName": "Artistic Denim Mills Limited",
    "icon": "test.svg"
  },
  {
    "id": 14,
    "symbol": "AGHA",
    "fullName": "Agha Steel Ind.Ltd",
    "icon": "test.svg"
  },
  {
    "id": 15,
    "symbol": "AGIC",
    "fullName": "Askari General Insurance Company Limited",
    "icon": "test.svg"
  },
  {
    "id": 17,
    "symbol": "AGIL",
    "fullName": "Agriauto Industries Limited",
    "icon": "test.svg"
  },
  {
    "id": 18,
    "symbol": "AGL",
    "fullName": "Agritech Limited",
    "icon": "test.svg"
  },
  {
    "id": 19,
    "symbol": "AGLNCPS",
    "fullName": "Agritech Non-Voting (Pref) Class A",
    "icon": "test.svg"
  },
  {
    "id": 20,
    "symbol": "AGP",
    "fullName": "AGP Limited",
    "icon": "test.svg"
  },
  {
    "id": 21,
    "symbol": "AGSML",
    "fullName": "Abdullah Shah Ghazi Sugar Mills Limited",
    "icon": "test.svg"
  },
  {
    "id": 22,
    "symbol": "AGTL",
    "fullName": "Al-Ghazi Tractors Limited",
    "icon": "test.svg"
  },
  {
    "id": 23,
    "symbol": "AHCL",
    "fullName": "Arif Habib Corporation Limited",
    "icon": "test.svg"
  },
  {
    "id": 24,
    "symbol": "AHL",
    "fullName": "Arif Habib Limited",
    "icon": "test.svg"
  },
  {
    "id": 25,
    "symbol": "AHTM",
    "fullName": "Ahmad Hassan Textile Mills Limited",
    "icon": "test.svg"
  },
  {
    "id": 26,
    "symbol": "AICL",
    "fullName": "Adamjee Insurance Company Limited",
    "icon": "test.svg"
  },
  {
    "id": 27,
    "symbol": "AIRLINK",
    "fullName": "Air Link Communication Limited",
    "icon": "test.svg"
  },
  {
    "id": 28,
    "symbol": "AKBL",
    "fullName": "Askari Bank Limited",
    "icon": "test.svg"
  },
  {
    "id": 29,
    "symbol": "AKDHL",
    "fullName": "AKD Hospitality Limited",
    "icon": "test.svg"
  },
  {
    "id": 30,
    "symbol": "AKDSL",
    "fullName": "AKD Securities Limited",
    "icon": "test.svg"
  },
  {
    "id": 31,
    "symbol": "AKGL",
    "fullName": "Al-Khair Gadoon Limited",
    "icon": "test.svg"
  },
  {
    "id": 32,
    "symbol": "ALAC",
    "fullName": "Askari Life Assurance Company Limited",
    "icon": "test.svg"
  },
  {
    "id": 33,
    "symbol": "ALIFE",
    "fullName": "Adamjee Life Assurance Company Limited",
    "icon": "test.svg"
  },
  {
    "id": 34,
    "symbol": "ALNRS",
    "fullName": "Al-Noor Sugar Mills Limited",
    "icon": "test.svg"
  },
  {
    "id": 35,
    "symbol": "ALTN",
    "fullName": "Altern Energy Limited",
    "icon": "test.svg"
  },
  {
    "id": 36,
    "symbol": "AMBL",
    "fullName": "Apna Microfinance Bank Limited",
    "icon": "test.svg"
  },
  {
    "id": 37,
    "symbol": "AMSL",
    "fullName": "Al-Mal Securities & Services Limited(DEF)",
    "icon": "test.svg"
  },
  {
    "id": 38,
    "symbol": "AMTEX",
    "fullName": "Amtex Limited(DEF)",
    "icon": "test.svg"
  },
  {
    "id": 39,
    "symbol": "ANL",
    "fullName": "Azgard Nine Limited",
    "icon": "test.svg"
  },
  {
    "id": 40,
    "symbol": "ANLNV",
    "fullName": "Azgard Nine Non-Voting Ordinary Shares",
    "icon": "test.svg"
  },
  {
    "id": 41,
    "symbol": "ANLPS",
    "fullName": "Azgard Nine 8.95%(Pref)",
    "icon": "test.svg"
  },
  {
    "id": 42,
    "symbol": "ANNT",
    "fullName": "Annoor Textile Mills Limited(DEF)",
    "icon": "test.svg"
  },
  {
    "id": 43,
    "symbol": "ANSM",
    "fullName": "Ansari Sugar Mills Limited",
    "icon": "test.svg"
  },
  {
    "id": 44,
    "symbol": "ANTM",
    "fullName": "AN Textile Mills Limited",
    "icon": "test.svg"
  },
  {
    "id": 45,
    "symbol": "APL",
    "fullName": "Attock Petroleum Limited",
    "icon": "test.svg"
  },
  {
    "id": 46,
    "symbol": "APOT",
    "fullName": "Apollo Textile Mills Limited(DEF)",
    "icon": "test.svg"
  },
  {
    "id": 47,
    "symbol": "ARCTM",
    "fullName": "Arctic Textile Mills Limited",
    "icon": "test.svg"
  },
  {
    "id": 48,
    "symbol": "ARMG",
    "fullName": "ARM Green Industries Limited",
    "icon": "test.svg"
  },
  {
    "id": 49,
    "symbol": "ARPAK",
    "fullName": "Arpak International Investments Ltd.",
    "icon": "test.svg"
  },
  {
    "id": 50,
    "symbol": "ARPL",
    "fullName": "Archroma Pakistan Limited",
    "icon": "test.svg"
  },
  {
    "id": 51,
    "symbol": "ARUJ",
    "fullName": "Aruj Industries Limited(DEF)",
    "icon": "test.svg"
  },
  {
    "id": 52,
    "symbol": "ASC",
    "fullName": "Al Shaheer Corporation Limited(DEF)",
    "icon": "test.svg"
  },
  {
    "id": 53,
    "symbol": "ASHT",
    "fullName": "Ashfaq Textile Mills Limited",
    "icon": "test.svg"
  },
  {
    "id": 54,
    "symbol": "ASIC",
    "fullName": "Asia Insurance Company Limited",
    "icon": "test.svg"
  },
  {
    "id": 55,
    "symbol": "ASL",
    "fullName": "Aisha Steel Mills Limited",
    "icon": "test.svg"
  },
  {
    "id": 57,
    "symbol": "ASLPS",
    "fullName": "Aisha Steel Convertible (Pref)",
    "icon": "test.svg"
  },
  {
    "id": 58,
    "symbol": "ASTL",
    "fullName": "Amreli Steels Limited",
    "icon": "test.svg"
  },
  {
    "id": 59,
    "symbol": "ASTM",
    "fullName": "Asim Textile Mills Limited",
    "icon": "test.svg"
  },
  {
    "id": 60,
    "symbol": "ATBA",
    "fullName": "Atlas Battery Limited",
    "icon": "test.svg"
  },
  {
    "id": 61,
    "symbol": "ATIL",
    "fullName": "Atlas Insurance Limited",
    "icon": "test.svg"
  },
  {
    "id": 62,
    "symbol": "ATLH",
    "fullName": "Atlas Honda Limited",
    "icon": "test.svg"
  },
  {
    "id": 63,
    "symbol": "ATRL",
    "fullName": "Attock Refinery Limited",
    "icon": "test.svg"
  },
  {
    "id": 64,
    "symbol": "AVN",
    "fullName": "Avanceon Limited",
    "icon": "test.svg"
  },
  {
    "id": 65,
    "symbol": "AWTX",
    "fullName": "Allawasaya Tex. & Finishing Mills Ltd",
    "icon": "test.svg"
  },
  {
    "id": 66,
    "symbol": "AZMT",
    "fullName": "Azmat Textile Mills Limited(DEF)",
    "icon": "test.svg"
  },
  {
    "id": 67,
    "symbol": "BAFL",
    "fullName": "Bank Alfalah Limited",
    "icon": "test.svg"
  },
  {
    "id": 68,
    "symbol": "BAFS",
    "fullName": "Baba Farid Sugar Mills Limited",
    "icon": "test.svg"
  },
  {
    "id": 69,
    "symbol": "BAHL",
    "fullName": "Bank AL Habib Limited",
    "icon": "test.svg"
  },
  {
    "id": 70,
    "symbol": "BAPL",
    "fullName": "Bawany Air Products Limited",
    "icon": "test.svg"
  },
  {
    "id": 71,
    "symbol": "BATA",
    "fullName": "Bata Pakistan Limited",
    "icon": "test.svg"
  },
  {
    "id": 72,
    "symbol": "BBFL",
    "fullName": "Big Bird Foods Limited",
    "icon": "test.svg"
  },
  {
    "id": 73,
    "symbol": "BCL",
    "fullName": "Bolan Castings Limited",
    "icon": "test.svg"
  },
  {
    "id": 74,
    "symbol": "BECO",
    "fullName": "Beco Steel Limited",
    "icon": "test.svg"
  },
  {
    "id": 75,
    "symbol": "BELA",
    "fullName": "Bela Automotives Limited(DEF)",
    "icon": "test.svg"
  },
  {
    "id": 76,
    "symbol": "BERG",
    "fullName": "Berger Paints Pakistan Limited",
    "icon": "test.svg"
  },
  {
    "id": 77,
    "symbol": "BFAGRO",
    "fullName": "Barkat Frisian Agro Limited",
    "icon": "test.svg"
  },
  {
    "id": 78,
    "symbol": "BFBIO",
    "fullName": "BF Biosciences Limited",
    "icon": "test.svg"
  },
  {
    "id": 79,
    "symbol": "BFMOD",
    "fullName": "B.F. Modaraba",
    "icon": "test.svg"
  },
  {
    "id": 80,
    "symbol": "BGL",
    "fullName": "Baluchistan Glass Limited",
    "icon": "test.svg"
  },
  {
    "id": 81,
    "symbol": "BHAT",
    "fullName": "Bhanero Textile Mills Limited",
    "icon": "test.svg"
  },
  {
    "id": 82,
    "symbol": "BIFO",
    "fullName": "Biafo Industries Limited",
    "icon": "test.svg"
  },
  {
    "id": 83,
    "symbol": "BIIC",
    "fullName": "Business & Industrial Insurance Company(DEF)",
    "icon": "test.svg"
  },
  {
    "id": 84,
    "symbol": "BIPL",
    "fullName": "BankIslami Pakistan Limited",
    "icon": "test.svg"
  },
  {
    "id": 85,
    "symbol": "BLUEX",
    "fullName": "Blue-Ex Limited",
    "icon": "test.svg"
  },
  {
    "id": 86,
    "symbol": "BML",
    "fullName": "Bank Makramah Limited",
    "icon": "test.svg"
  },
  {
    "id": 87,
    "symbol": "BNL",
    "fullName": "Bunnys Limited",
    "icon": "test.svg"
  },
  {
    "id": 88,
    "symbol": "BNWM",
    "fullName": "Bannu Woollen Mills Limited",
    "icon": "test.svg"
  },
  {
    "id": 89,
    "symbol": "BOK",
    "fullName": "The Bank of Khyber",
    "icon": "test.svg"
  },
  {
    "id": 90,
    "symbol": "BOP",
    "fullName": "The Bank of Punjab",
    "icon": "test.svg"
  },
  {
    "id": 91,
    "symbol": "BPL",
    "fullName": "Burshane LPG (Pakistan) Limited",
    "icon": "test.svg"
  },
  {
    "id": 92,
    "symbol": "BRRG",
    "fullName": "B.R.R Guardian Limited",
    "icon": "test.svg"
  },
  {
    "id": 93,
    "symbol": "BTL",
    "fullName": "Blessed Textiles Limited",
    "icon": "test.svg"
  },
  {
    "id": 94,
    "symbol": "BUXL",
    "fullName": "Buxly Paints Limited",
    "icon": "test.svg"
  },
  {
    "id": 95,
    "symbol": "BWCL",
    "fullName": "Bestway Cement Limited",
    "icon": "test.svg"
  },
  {
    "id": 96,
    "symbol": "BWHL",
    "fullName": "Baluchistan Wheels Limited",
    "icon": "test.svg"
  },
  {
    "id": 97,
    "symbol": "CCM",
    "fullName": "Crescent Cotton Mills Limited",
    "icon": "test.svg"
  },
  {
    "id": 98,
    "symbol": "CENI",
    "fullName": "Century Insurance Company Limited",
    "icon": "test.svg"
  },
  {
    "id": 99,
    "symbol": "CEPB",
    "fullName": "Century Paper & Board Mills Limited",
    "icon": "test.svg"
  },
  {
    "id": 100,
    "symbol": "CFL",
    "fullName": "Crescent Fibres Limited",
    "icon": "test.svg"
  },
  {
    "id": 101,
    "symbol": "CHAS",
    "fullName": "Chashma Sugar Mills Limited",
    "icon": "test.svg"
  },
  {
    "id": 102,
    "symbol": "CHBL",
    "fullName": "Chenab Limited",
    "icon": "test.svg"
  },
  {
    "id": 103,
    "symbol": "CHCC",
    "fullName": "Cherat Cement Company Limited",
    "icon": "test.svg"
  },
  {
    "id": 104,
    "symbol": "CJPL",
    "fullName": "Crescent Jute Products Limited(DEF)",
    "icon": "test.svg"
  },
  {
    "id": 105,
    "symbol": "CLCPS",
    "fullName": "Chenab Limited (Pref)",
    "icon": "test.svg"
  },
  {
    "id": 106,
    "symbol": "CLOV",
    "fullName": "Clover Pakistan Limited",
    "icon": "test.svg"
  },
  {
    "id": 107,
    "symbol": "CLVL",
    "fullName": "Cordoba Logistics & Ventures Limited",
    "icon": "test.svg"
  },
  {
    "id": 108,
    "symbol": "CNERGY",
    "fullName": "Cnergyico PK  Limited",
    "icon": "test.svg"
  },
  {
    "id": 109,
    "symbol": "COLG",
    "fullName": "Colgate-Palmolive (Pakistan) Limited",
    "icon": "test.svg"
  },
  {
    "id": 110,
    "symbol": "CPHL",
    "fullName": "Citi Pharma Ltd.",
    "icon": "test.svg"
  },
  {
    "id": 111,
    "symbol": "CPPL",
    "fullName": "Cherat Packaging Limited",
    "icon": "test.svg"
  },
  {
    "id": 112,
    "symbol": "CRTM",
    "fullName": "The Crescent Textile Mills Limited",
    "icon": "test.svg"
  },
  {
    "id": 113,
    "symbol": "CSAP",
    "fullName": "Crescent Steel & Allied Products Limited",
    "icon": "test.svg"
  },
  {
    "id": 114,
    "symbol": "CSIL",
    "fullName": "Crescent Star Insurance Limited",
    "icon": "test.svg"
  },
  {
    "id": 115,
    "symbol": "CTM",
    "fullName": "Colony Textile Mills Limited",
    "icon": "test.svg"
  },
  {
    "id": 116,
    "symbol": "DAAG",
    "fullName": "Data Agro Limited",
    "icon": "test.svg"
  },
  {
    "id": 117,
    "symbol": "DADX",
    "fullName": "Dadex Eternit Limited",
    "icon": "test.svg"
  },
  {
    "id": 118,
    "symbol": "DBCI",
    "fullName": "Dadabhoy Cement Industries Limited(DEF)",
    "icon": "test.svg"
  },
  {
    "id": 119,
    "symbol": "DBSL",
    "fullName": "Dadabhoy Sack Limited(DEF)",
    "icon": "test.svg"
  },
  {
    "id": 120,
    "symbol": "DCL",
    "fullName": "Dewan Cement Limited",
    "icon": "test.svg"
  },
  {
    "id": 121,
    "symbol": "DCR",
    "fullName": "Dolmen City REIT",
    "icon": "test.svg"
  },
  {
    "id": 122,
    "symbol": "DCTL",
    "fullName": "Dadabhoy Construction Technology Limited(DEF)",
    "icon": "test.svg"
  },
  {
    "id": 123,
    "symbol": "DEL",
    "fullName": "Dawood Equities Limited",
    "icon": "test.svg"
  },
  {
    "id": 124,
    "symbol": "DFML",
    "fullName": "Dewan Farooque Motors Limited",
    "icon": "test.svg"
  },
  {
    "id": 125,
    "symbol": "DFSM",
    "fullName": "Dewan Farooque Spinning Mills Limited",
    "icon": "test.svg"
  },
  {
    "id": 126,
    "symbol": "DGKC",
    "fullName": "D.G. Khan Cement Company Limited",
    "icon": "test.svg"
  },
  {
    "id": 127,
    "symbol": "DIIL",
    "fullName": "Diamond Industries Limited",
    "icon": "test.svg"
  },
  {
    "id": 128,
    "symbol": "DINT",
    "fullName": "Din Textile Mills Limited",
    "icon": "test.svg"
  },
  {
    "id": 129,
    "symbol": "DKTM",
    "fullName": "Dewan Khalid Textile Mills Limited(DEF)",
    "icon": "test.svg"
  },
  {
    "id": 130,
    "symbol": "DLL",
    "fullName": "Dawood Lawrencepur Limited",
    "icon": "test.svg"
  },
  {
    "id": 131,
    "symbol": "DMC",
    "fullName": "D.M. Corporation Limited.",
    "icon": "test.svg"
  },
  {
    "id": 132,
    "symbol": "DMTM",
    "fullName": "Dewan Mushtaq Textile Mills Limited(DEF)",
    "icon": "test.svg"
  },
  {
    "id": 133,
    "symbol": "DNCC",
    "fullName": "Dandot Cement Company Limited",
    "icon": "test.svg"
  },
  {
    "id": 134,
    "symbol": "DOL",
    "fullName": "Descon Oxychem Limited",
    "icon": "test.svg"
  },
  {
    "id": 135,
    "symbol": "DSFL",
    "fullName": "Dewan Salman Fibre Limited(DEF)",
    "icon": "test.svg"
  },
  {
    "id": 136,
    "symbol": "DSIL",
    "fullName": "D.S. Industries Limited",
    "icon": "test.svg"
  },
  {
    "id": 137,
    "symbol": "DSL",
    "fullName": "Dost Steels Limited(DEF)",
    "icon": "test.svg"
  },
  {
    "id": 138,
    "symbol": "DWAE",
    "fullName": "Dewan Automotive Engineering Limited(DEF)",
    "icon": "test.svg"
  },
  {
    "id": 139,
    "symbol": "DWSM",
    "fullName": "Dewan Sugar Mills Limited(DEF)",
    "icon": "test.svg"
  },
  {
    "id": 140,
    "symbol": "DWTM",
    "fullName": "Dewan Textile Mills Limited(DEF)",
    "icon": "test.svg"
  },
  {
    "id": 141,
    "symbol": "DYNO",
    "fullName": "Dynea Pakistan Limited",
    "icon": "test.svg"
  },
  {
    "id": 142,
    "symbol": "ECOP",
    "fullName": "Ecopack Limited",
    "icon": "test.svg"
  },
  {
    "id": 143,
    "symbol": "EFERT",
    "fullName": "Engro Fertilizers Limited",
    "icon": "test.svg"
  },
  {
    "id": 144,
    "symbol": "EFUG",
    "fullName": "EFU General Insurance Limited",
    "icon": "test.svg"
  },
  {
    "id": 145,
    "symbol": "EFUL",
    "fullName": "EFU Life Assurance Limited",
    "icon": "test.svg"
  },
  {
    "id": 146,
    "symbol": "ELCM",
    "fullName": "Elahi Cotton Mills Limited",
    "icon": "test.svg"
  },
  {
    "id": 147,
    "symbol": "ELSM",
    "fullName": "Ellcot Spinning Mills Limited",
    "icon": "test.svg"
  },
  {
    "id": 148,
    "symbol": "EMCO",
    "fullName": "Emco Industries Limited",
    "icon": "test.svg"
  },
  {
    "id": 149,
    "symbol": "ENGL",
    "fullName": "English Leasing Limited(DEF)",
    "icon": "test.svg"
  },
  {
    "id": 150,
    "symbol": "ENGROH",
    "fullName": "Engro Holdings Limited",
    "icon": "test.svg"
  },
  {
    "id": 151,
    "symbol": "EPCL",
    "fullName": "Engro Polymer & Chemicals Limited",
    "icon": "test.svg"
  },
  {
    "id": 152,
    "symbol": "EPCLPS",
    "fullName": "Engro Poly(Pref)",
    "icon": "test.svg"
  },
  {
    "id": 153,
    "symbol": "EPQL",
    "fullName": "Engro Powergen Qadirpur Limited",
    "icon": "test.svg"
  },
  {
    "id": 154,
    "symbol": "ESBL",
    "fullName": "Escorts Investment Bank Limited(DEF)",
    "icon": "test.svg"
  },
  {
    "id": 155,
    "symbol": "EWIC",
    "fullName": "East West Insurance Company Limited",
    "icon": "test.svg"
  },
  {
    "id": 156,
    "symbol": "EXIDE",
    "fullName": "Exide Pakistan Limited",
    "icon": "test.svg"
  },
  {
    "id": 157,
    "symbol": "FABL",
    "fullName": "Faysal Bank Limited",
    "icon": "test.svg"
  },
  {
    "id": 158,
    "symbol": "FAEL",
    "fullName": "Fatima Enterprises Limited(DEF)",
    "icon": "test.svg"
  },
  {
    "id": 159,
    "symbol": "FANM",
    "fullName": "First Al-Noor Modaraba",
    "icon": "test.svg"
  },
  {
    "id": 160,
    "symbol": "FASM",
    "fullName": "Faisal Spinning Mills Limited",
    "icon": "test.svg"
  },
  {
    "id": 161,
    "symbol": "FATIMA",
    "fullName": "Fatima Fertilizer Company Limited",
    "icon": "test.svg"
  },
  {
    "id": 162,
    "symbol": "FCCL",
    "fullName": "Fauji Cement Company Limited",
    "icon": "test.svg"
  },
  {
    "id": 163,
    "symbol": "FCEL",
    "fullName": "First Capital Equities Limited(DEF)",
    "icon": "test.svg"
  },
  {
    "id": 164,
    "symbol": "FCEPL",
    "fullName": "Frieslandcampina Engro Pakistan Limited",
    "icon": "test.svg"
  },
  {
    "id": 165,
    "symbol": "FCIBL",
    "fullName": "First Credit and Investment Bank Limited",
    "icon": "test.svg"
  },
  {
    "id": 166,
    "symbol": "FCL",
    "fullName": "Fast Cables Limited",
    "icon": "test.svg"
  },
  {
    "id": 167,
    "symbol": "FCONM",
    "fullName": "First Constellation Modaraba",
    "icon": "test.svg"
  },
  {
    "id": 168,
    "symbol": "FCSC",
    "fullName": "First Capital Securities Corporation",
    "icon": "test.svg"
  },
  {
    "id": 169,
    "symbol": "FDPL",
    "fullName": "First Dawood Properties Limited",
    "icon": "test.svg"
  },
  {
    "id": 170,
    "symbol": "FECM",
    "fullName": "First Elite Capital Modaraba",
    "icon": "test.svg"
  },
  {
    "id": 171,
    "symbol": "FECTC",
    "fullName": "Fecto Cement Limited",
    "icon": "test.svg"
  },
  {
    "id": 172,
    "symbol": "FEM",
    "fullName": "First Equity Modaraba",
    "icon": "test.svg"
  },
  {
    "id": 173,
    "symbol": "FEROZ",
    "fullName": "Ferozsons Laboratories Limited",
    "icon": "test.svg"
  },
  {
    "id": 174,
    "symbol": "FFC",
    "fullName": "Fauji Fertilizer Company Limited",
    "icon": "test.svg"
  },
  {
    "id": 175,
    "symbol": "FFL",
    "fullName": "Fauji Foods Limited",
    "icon": "test.svg"
  },
  {
    "id": 176,
    "symbol": "FFLM",
    "fullName": "First Fidelity Leasing Modaraba",
    "icon": "test.svg"
  },
  {
    "id": 177,
    "symbol": "FHAM",
    "fullName": "First Habib Modaraba",
    "icon": "test.svg"
  },
  {
    "id": 178,
    "symbol": "FIBLM",
    "fullName": "First IBL Modaraba",
    "icon": "test.svg"
  },
  {
    "id": 179,
    "symbol": "FIL",
    "fullName": "Fateh Industries Limited(DEF)",
    "icon": "test.svg"
  },
  {
    "id": 180,
    "symbol": "FIM",
    "fullName": "First Investec Modaraba(DEF)",
    "icon": "test.svg"
  },
  {
    "id": 181,
    "symbol": "FIMM",
    "fullName": "First Imrooz Modaraba",
    "icon": "test.svg"
  },
  {
    "id": 182,
    "symbol": "FLYNG",
    "fullName": "Flying Cement Company Limited",
    "icon": "test.svg"
  },
  {
    "id": 183,
    "symbol": "FML",
    "fullName": "Feroze1888 Mills Limited",
    "icon": "test.svg"
  },
  {
    "id": 184,
    "symbol": "FNBM",
    "fullName": "First National Bank Modaraba(DEF)",
    "icon": "test.svg"
  },
  {
    "id": 185,
    "symbol": "FNEL",
    "fullName": "First National Equities Limited",
    "icon": "test.svg"
  },
  {
    "id": 186,
    "symbol": "FPJM",
    "fullName": "First Punjab Modaraba",
    "icon": "test.svg"
  },
  {
    "id": 187,
    "symbol": "FPRM",
    "fullName": "First Paramount Modaraba",
    "icon": "test.svg"
  },
  {
    "id": 188,
    "symbol": "FRCL",
    "fullName": "Frontier Ceramics Limited",
    "icon": "test.svg"
  },
  {
    "id": 189,
    "symbol": "FRSM",
    "fullName": "Faran Sugar Mills Limited",
    "icon": "test.svg"
  },
  {
    "id": 190,
    "symbol": "FSWL",
    "fullName": "Fateh Sports Wear Limited(DEF)",
    "icon": "test.svg"
  },
  {
    "id": 191,
    "symbol": "FTHM",
    "fullName": "Fateh Textile Mills Limited(DEF)",
    "icon": "test.svg"
  },
  {
    "id": 192,
    "symbol": "FTMM",
    "fullName": "First Treet Manufacturing Modaraba",
    "icon": "test.svg"
  },
  {
    "id": 193,
    "symbol": "FTSM",
    "fullName": "First Tri-Star Modaraba",
    "icon": "test.svg"
  },
  {
    "id": 194,
    "symbol": "FZCM",
    "fullName": "Fazal Cloth Mills Limited",
    "icon": "test.svg"
  },
  {
    "id": 195,
    "symbol": "GADT",
    "fullName": "Gadoon Textile Mills Limited",
    "icon": "test.svg"
  },
  {
    "id": 196,
    "symbol": "GAL",
    "fullName": "Ghandhara Automobiles Limited",
    "icon": "test.svg"
  },
  {
    "id": 197,
    "symbol": "GAMON",
    "fullName": "Gammon Pakistan Limited(DEF)",
    "icon": "test.svg"
  },
  {
    "id": 198,
    "symbol": "GATI",
    "fullName": "Gatron (Industries) Limited",
    "icon": "test.svg"
  },
  {
    "id": 199,
    "symbol": "GATM",
    "fullName": "Gul Ahmed Textile Mills Limited",
    "icon": "test.svg"
  },
  {
    "id": 200,
    "symbol": "GCIL",
    "fullName": "Ghani Chemical Industries Limited",
    "icon": "test.svg"
  },
  {
    "id": 201,
    "symbol": "GCWL",
    "fullName": "Ghani Chemworld Limited",
    "icon": "test.svg"
  },
  {
    "id": 203,
    "symbol": "GDL",
    "fullName": "Ghani Dairies Limited",
    "icon": "test.svg"
  },
  {
    "id": 204,
    "symbol": "GEMBCEM",
    "fullName": "Burj Clean Energy Modaraba(GEM)",
    "icon": "test.svg"
  },
  {
    "id": 205,
    "symbol": "GEMMEL",
    "fullName": "Mughal Energy Limited(GEM)",
    "icon": "test.svg"
  },
  {
    "id": 206,
    "symbol": "GEMNETS",
    "fullName": "Nets International Communication Limited",
    "icon": "test.svg"
  },
  {
    "id": 207,
    "symbol": "GEMPACRA",
    "fullName": "The Pakistan Credit Rating Agency Ltd",
    "icon": "test.svg"
  },
  {
    "id": 208,
    "symbol": "GEMPAPL",
    "fullName": "Pak Agro Packaging Limited(GEM)",
    "icon": "test.svg"
  },
  {
    "id": 209,
    "symbol": "GFIL",
    "fullName": "Ghazi Fabrics International Limited",
    "icon": "test.svg"
  },
  {
    "id": 210,
    "symbol": "GGGL",
    "fullName": "Ghani Global Glass Limited",
    "icon": "test.svg"
  },
  {
    "id": 211,
    "symbol": "GGL",
    "fullName": "Ghani Global Holdings Limited",
    "icon": "test.svg"
  },
  {
    "id": 212,
    "symbol": "GHGL",
    "fullName": "Ghani Glass Limited(XD)",
    "icon": "test.svg"
  },
  {
    "id": 213,
    "symbol": "GHNI",
    "fullName": "Ghandhara Industries Limited",
    "icon": "test.svg"
  },
  {
    "id": 214,
    "symbol": "GIL",
    "fullName": "Good Luck Industries Ltd.",
    "icon": "test.svg"
  },
  {
    "id": 215,
    "symbol": "GLAXO",
    "fullName": "GlaxoSmithKline Pakistan Limited",
    "icon": "test.svg"
  },
  {
    "id": 216,
    "symbol": "GLOT",
    "fullName": "Globe Textile Mills Limited(DEF)",
    "icon": "test.svg"
  },
  {
    "id": 217,
    "symbol": "GOC",
    "fullName": "GOC (Pak) Limited.",
    "icon": "test.svg"
  },
  {
    "id": 218,
    "symbol": "GRR",
    "fullName": "Globe Residency REIT",
    "icon": "test.svg"
  },
  {
    "id": 219,
    "symbol": "GRYL",
    "fullName": "Grays Leasing Limited",
    "icon": "test.svg"
  },
  {
    "id": 220,
    "symbol": "GSPM",
    "fullName": "Gulshan Spinning Mills Limited(DEF)",
    "icon": "test.svg"
  },
  {
    "id": 221,
    "symbol": "GTYR",
    "fullName": "Ghandhara Tyre & Rubber Company Limited",
    "icon": "test.svg"
  },
  {
    "id": 222,
    "symbol": "GUSM",
    "fullName": "Gulistan Spinning Mills Limited(DEF)",
    "icon": "test.svg"
  },
  {
    "id": 223,
    "symbol": "GUTM",
    "fullName": "Gulistan Textile Mills Limited(DEF)",
    "icon": "test.svg"
  },
  {
    "id": 224,
    "symbol": "GVGL",
    "fullName": "Ghani Value Glass Limited",
    "icon": "test.svg"
  },
  {
    "id": 225,
    "symbol": "GWLC",
    "fullName": "Gharibwal Cement Limited",
    "icon": "test.svg"
  },
  {
    "id": 226,
    "symbol": "HABSM",
    "fullName": "Habib Sugar Mills Limited",
    "icon": "test.svg"
  },
  {
    "id": 227,
    "symbol": "HADC",
    "fullName": "Haydari Construction Company Limited(DEF)",
    "icon": "test.svg"
  },
  {
    "id": 228,
    "symbol": "HAEL",
    "fullName": "Hala Enterprises Limited",
    "icon": "test.svg"
  },
  {
    "id": 229,
    "symbol": "HAFL",
    "fullName": "Hafiz Limited",
    "icon": "test.svg"
  },
  {
    "id": 230,
    "symbol": "HAJT",
    "fullName": "Hajra Textile Mills Limited(DEF)",
    "icon": "test.svg"
  },
  {
    "id": 231,
    "symbol": "HALEON",
    "fullName": "Haleon Pakistan Limited",
    "icon": "test.svg"
  },
  {
    "id": 232,
    "symbol": "HASCOL",
    "fullName": "Hascol Petroleum Limited(DEF)",
    "icon": "test.svg"
  },
  {
    "id": 233,
    "symbol": "HATM",
    "fullName": "Hamid Textile Mills Limited(DEF)",
    "icon": "test.svg"
  },
  {
    "id": 234,
    "symbol": "HBL",
    "fullName": "Habib Bank Limited",
    "icon": "test.svg"
  },
  {
    "id": 235,
    "symbol": "HBLTETF",
    "fullName": "HBL Total Treasury (ETF)(XD)",
    "icon": "test.svg"
  },
  {
    "id": 236,
    "symbol": "HCAR",
    "fullName": "Honda Atlas Cars (Pakistan) Limited(XD)",
    "icon": "test.svg"
  },
  {
    "id": 237,
    "symbol": "HGFA",
    "fullName": "HBL Growth Fund(XD)",
    "icon": "test.svg"
  },
  {
    "id": 238,
    "symbol": "HICL",
    "fullName": "Habib Insurance Company Limited",
    "icon": "test.svg"
  },
  {
    "id": 239,
    "symbol": "HIFA",
    "fullName": "HBL Investment Fund(XD)",
    "icon": "test.svg"
  },
  {
    "id": 240,
    "symbol": "HINO",
    "fullName": "Hinopak Motors Limited",
    "icon": "test.svg"
  },
  {
    "id": 241,
    "symbol": "HINOON",
    "fullName": "Highnoon Laboratories Limited",
    "icon": "test.svg"
  },
  {
    "id": 242,
    "symbol": "HIRAT",
    "fullName": "Hira Textile Mills Limited(DEF)",
    "icon": "test.svg"
  },
  {
    "id": 243,
    "symbol": "HKKT",
    "fullName": "Hakkim Textile Mills Limited(DEF)",
    "icon": "test.svg"
  },
  {
    "id": 244,
    "symbol": "HMB",
    "fullName": "Habib Metropolitan Bank Limited",
    "icon": "test.svg"
  },
  {
    "id": 245,
    "symbol": "HMIM",
    "fullName": "Haji Mohammad Ismail Mills Limited(DEF)",
    "icon": "test.svg"
  },
  {
    "id": 246,
    "symbol": "HPL",
    "fullName": "Hoechst Pakistan Limited",
    "icon": "test.svg"
  },
  {
    "id": 247,
    "symbol": "HRPL",
    "fullName": "Habib Rice Product Limited.",
    "icon": "test.svg"
  },
  {
    "id": 248,
    "symbol": "HSPI",
    "fullName": "Huffaz Seamless Pipe Industries Limited(DEF)",
    "icon": "test.svg"
  },
  {
    "id": 249,
    "symbol": "HTL",
    "fullName": "Hi-Tech Lubricants Limited",
    "icon": "test.svg"
  },
  {
    "id": 250,
    "symbol": "HUBC",
    "fullName": "The Hub Power Company Limited",
    "icon": "test.svg"
  },
  {
    "id": 251,
    "symbol": "HUMNL",
    "fullName": "Hum Network Limited",
    "icon": "test.svg"
  },
  {
    "id": 252,
    "symbol": "HUSI",
    "fullName": "Husein Industries Limited",
    "icon": "test.svg"
  },
  {
    "id": 253,
    "symbol": "HWQS",
    "fullName": "Haseeb Waqas Sugar Mills Limited(DEF)",
    "icon": "test.svg"
  },
  {
    "id": 254,
    "symbol": "IBFL",
    "fullName": "Ibrahim Fibres Limited",
    "icon": "test.svg"
  },
  {
    "id": 255,
    "symbol": "IBLHL",
    "fullName": "IBL HealthCare Limited",
    "icon": "test.svg"
  },
  {
    "id": 256,
    "symbol": "ICCI",
    "fullName": "ICC Industries Limited",
    "icon": "test.svg"
  },
  {
    "id": 257,
    "symbol": "ICIBL",
    "fullName": "Invest Capital Investment Bank Limited",
    "icon": "test.svg"
  },
  {
    "id": 258,
    "symbol": "ICL",
    "fullName": "Ittehad Chemicals Limted",
    "icon": "test.svg"
  },
  {
    "id": 259,
    "symbol": "IDRT",
    "fullName": "Idrees Textile Mills Limited",
    "icon": "test.svg"
  },
  {
    "id": 260,
    "symbol": "IDSM",
    "fullName": "Ideal Spinning Mills Limited",
    "icon": "test.svg"
  },
  {
    "id": 261,
    "symbol": "IDYM",
    "fullName": "Indus Dyeing & Manufacturing Co. Limited",
    "icon": "test.svg"
  },
  {
    "id": 262,
    "symbol": "IGIHL",
    "fullName": "IGI Holdings Limited",
    "icon": "test.svg"
  },
  {
    "id": 263,
    "symbol": "IGIL",
    "fullName": "IGI Life Insurance Limited",
    "icon": "test.svg"
  },
  {
    "id": 264,
    "symbol": "ILP",
    "fullName": "Interloop Limited",
    "icon": "test.svg"
  },
  {
    "id": 265,
    "symbol": "IMAGE",
    "fullName": "Image Pakistan Limited",
    "icon": "test.svg"
  },
  {
    "id": 266,
    "symbol": "IML",
    "fullName": "Imperial  Limited(DEF)",
    "icon": "test.svg"
  },
  {
    "id": 267,
    "symbol": "IMS",
    "fullName": "Intermarket Securities Limited",
    "icon": "test.svg"
  },
  {
    "id": 268,
    "symbol": "INDU",
    "fullName": "Indus Motor Company Limited",
    "icon": "test.svg"
  },
  {
    "id": 269,
    "symbol": "INIL",
    "fullName": "International Industries Limited",
    "icon": "test.svg"
  },
  {
    "id": 270,
    "symbol": "INKL",
    "fullName": "International Knitwear Limited",
    "icon": "test.svg"
  },
  {
    "id": 271,
    "symbol": "INMF",
    "fullName": "Investec Mutual Fund Limited(DEF)",
    "icon": "test.svg"
  },
  {
    "id": 272,
    "symbol": "IPAK",
    "fullName": "International Packaging Films Limited(XB)",
    "icon": "test.svg"
  },
  {
    "id": 273,
    "symbol": "IREIT",
    "fullName": "Image Reit",
    "icon": "test.svg"
  },
  {
    "id": 274,
    "symbol": "ISIL",
    "fullName": "Ismail Industries Limited",
    "icon": "test.svg"
  },
  {
    "id": 275,
    "symbol": "ISL",
    "fullName": "International Steels Limited",
    "icon": "test.svg"
  },
  {
    "id": 276,
    "symbol": "ITANZ",
    "fullName": "Itanz Technologies Limited",
    "icon": "test.svg"
  },
  {
    "id": 277,
    "symbol": "ITTEFAQ",
    "fullName": "Ittefaq Iron Industries Limited",
    "icon": "test.svg"
  },
  {
    "id": 278,
    "symbol": "JATM",
    "fullName": "J.A. Textile Mills Limited",
    "icon": "test.svg"
  },
  {
    "id": 279,
    "symbol": "JDMT",
    "fullName": "Janana De Malucho Textile Mills Limited",
    "icon": "test.svg"
  },
  {
    "id": 280,
    "symbol": "JDWS",
    "fullName": "JDW Sugar Mills Limited",
    "icon": "test.svg"
  },
  {
    "id": 281,
    "symbol": "JGICL",
    "fullName": "Jubilee General Insurance Company Ltd.",
    "icon": "test.svg"
  },
  {
    "id": 282,
    "symbol": "JKSM",
    "fullName": "J.K. Spinning Mills Limited",
    "icon": "test.svg"
  },
  {
    "id": 283,
    "symbol": "JLICL",
    "fullName": "Jubilee Life Insurance Company Limited",
    "icon": "test.svg"
  },
  {
    "id": 284,
    "symbol": "JSBL",
    "fullName": "JS Bank Limited",
    "icon": "test.svg"
  },
  {
    "id": 285,
    "symbol": "JSCL",
    "fullName": "Jahangir Siddiqui & Co. Ltd.",
    "icon": "test.svg"
  },
  {
    "id": 286,
    "symbol": "JSGBETF",
    "fullName": "JS Global Banking Sector(ETF)",
    "icon": "test.svg"
  },
  {
    "id": 287,
    "symbol": "JSGCL",
    "fullName": "JS Global Capital Limited",
    "icon": "test.svg"
  },
  {
    "id": 288,
    "symbol": "JSIL",
    "fullName": "JS Investments Limited",
    "icon": "test.svg"
  },
  {
    "id": 289,
    "symbol": "JSMFETF",
    "fullName": "JS Momentum Factor Exchange Traded Fund",
    "icon": "test.svg"
  },
  {
    "id": 290,
    "symbol": "JSML",
    "fullName": "Jauharabad Sugar Mills Limited",
    "icon": "test.svg"
  },
  {
    "id": 291,
    "symbol": "JSRR",
    "fullName": "JS Rental REIT",
    "icon": "test.svg"
  },
  {
    "id": 292,
    "symbol": "JUBS",
    "fullName": "Jubilee Spinning & Weaving Mills Ltd.(DEF)",
    "icon": "test.svg"
  },
  {
    "id": 293,
    "symbol": "JVDC",
    "fullName": "Javedan Corporation Limited",
    "icon": "test.svg"
  },
  {
    "id": 294,
    "symbol": "JVDCPS",
    "fullName": "Javedan Corporation (Pref)",
    "icon": "test.svg"
  },
  {
    "id": 295,
    "symbol": "KAKL",
    "fullName": "Kaiser Arts & Krafts Limited(DEF)",
    "icon": "test.svg"
  },
  {
    "id": 296,
    "symbol": "KAPCO",
    "fullName": "Kot Addu Power Company Limited",
    "icon": "test.svg"
  },
  {
    "id": 297,
    "symbol": "KCL",
    "fullName": "Karam Ceramics Limited",
    "icon": "test.svg"
  },
  {
    "id": 298,
    "symbol": "KEL",
    "fullName": "K-Electric Limited",
    "icon": "test.svg"
  },
  {
    "id": 299,
    "symbol": "KHTC",
    "fullName": "Khyber Tobacco Company Limited",
    "icon": "test.svg"
  },
  {
    "id": 300,
    "symbol": "KHYT",
    "fullName": "Khyber Textile Mills Limited",
    "icon": "test.svg"
  },
  {
    "id": 301,
    "symbol": "KML",
    "fullName": "Kohinoor Mills Limited",
    "icon": "test.svg"
  },
  {
    "id": 302,
    "symbol": "KOHC",
    "fullName": "Kohat Cement Company Limited",
    "icon": "test.svg"
  },
  {
    "id": 303,
    "symbol": "KOHE",
    "fullName": "Kohinoor Energy Limited",
    "icon": "test.svg"
  },
  {
    "id": 304,
    "symbol": "KOHP",
    "fullName": "Kohinoor Power Company Limited",
    "icon": "test.svg"
  },
  {
    "id": 305,
    "symbol": "KOHTM",
    "fullName": "Kohat Textile Mills Limited",
    "icon": "test.svg"
  },
  {
    "id": 306,
    "symbol": "KOIL",
    "fullName": "Kohinoor Industries Limited",
    "icon": "test.svg"
  },
  {
    "id": 307,
    "symbol": "KOSM",
    "fullName": "Kohinoor Spinning Mills Limited",
    "icon": "test.svg"
  },
  {
    "id": 308,
    "symbol": "KPUS",
    "fullName": "Khairpur Sugar Mills Limited",
    "icon": "test.svg"
  },
  {
    "id": 309,
    "symbol": "KSBP",
    "fullName": "KSB Pumps Company Limited",
    "icon": "test.svg"
  },
  {
    "id": 310,
    "symbol": "KSTM",
    "fullName": "Khalid Siraj Textile Mills Limited(DEF)",
    "icon": "test.svg"
  },
  {
    "id": 311,
    "symbol": "KTML",
    "fullName": "Kohinoor Textile Mills Limited",
    "icon": "test.svg"
  },
  {
    "id": 312,
    "symbol": "LCI",
    "fullName": "Lucky Core Industries Limited",
    "icon": "test.svg"
  },
  {
    "id": 313,
    "symbol": "LEUL",
    "fullName": "Leather Up Limited",
    "icon": "test.svg"
  },
  {
    "id": 314,
    "symbol": "LIVEN",
    "fullName": "Liven Pharma Limited",
    "icon": "test.svg"
  },
  {
    "id": 315,
    "symbol": "LOADS",
    "fullName": "Loads Limited",
    "icon": "test.svg"
  },
  {
    "id": 316,
    "symbol": "LOTCHEM",
    "fullName": "Lotte Chemical Pakistan Limited",
    "icon": "test.svg"
  },
  {
    "id": 317,
    "symbol": "LPGL",
    "fullName": "Leiner Pak Gelatine Limited",
    "icon": "test.svg"
  },
  {
    "id": 318,
    "symbol": "LPL",
    "fullName": "Lalpir Power Limited",
    "icon": "test.svg"
  },
  {
    "id": 319,
    "symbol": "LSECL",
    "fullName": "LSE Capital Limited.",
    "icon": "test.svg"
  },
  {
    "id": 320,
    "symbol": "LSEFSL",
    "fullName": "LSE Financial Services Limited.",
    "icon": "test.svg"
  },
  {
    "id": 321,
    "symbol": "LSEVL",
    "fullName": "LSE Ventures Limited",
    "icon": "test.svg"
  },
  {
    "id": 322,
    "symbol": "LUCK",
    "fullName": "Lucky Cement Limited",
    "icon": "test.svg"
  },
  {
    "id": 323,
    "symbol": "MACFL",
    "fullName": "MACPAC Films Limited",
    "icon": "test.svg"
  },
  {
    "id": 324,
    "symbol": "MACTER",
    "fullName": "Macter International Limited",
    "icon": "test.svg"
  },
  {
    "id": 325,
    "symbol": "MARI",
    "fullName": "Mari Energies Limited",
    "icon": "test.svg"
  },
  {
    "id": 326,
    "symbol": "MCB",
    "fullName": "MCB Bank Limited",
    "icon": "test.svg"
  },
  {
    "id": 327,
    "symbol": "MCBIM",
    "fullName": "MCB Investment Management Limited.",
    "icon": "test.svg"
  },
  {
    "id": 328,
    "symbol": "MDTL",
    "fullName": "Media Times Limited",
    "icon": "test.svg"
  },
  {
    "id": 329,
    "symbol": "MEBL",
    "fullName": "Meezan Bank Limited",
    "icon": "test.svg",
    "currentPrice": 200,
    "annualDividend": 28,
    "dividendYield": 6
  },
  {
    "id": 330,
    "symbol": "MEHT",
    "fullName": "Mehmood Textile Mills Limited",
    "icon": "test.svg"
  },
  {
    "id": 331,
    "symbol": "MERIT",
    "fullName": "Merit Packaging Limited",
    "icon": "test.svg"
  },
  {
    "id": 332,
    "symbol": "MFFL",
    "fullName": "Mitchells Fruit Farms Limited",
    "icon": "test.svg"
  },
  {
    "id": 333,
    "symbol": "MFL",
    "fullName": "Matco Foods Limited",
    "icon": "test.svg"
  },
  {
    "id": 334,
    "symbol": "MFTM",
    "fullName": "Mohammad Farooq Textile Mills Limited(DEF)",
    "icon": "test.svg"
  },
  {
    "id": 335,
    "symbol": "MIIETF",
    "fullName": "Mahaana Islamic Index ETF(XD)",
    "icon": "test.svg"
  },
  {
    "id": 336,
    "symbol": "MIRKS",
    "fullName": "Mirpurkhas Sugar Mills Limited",
    "icon": "test.svg"
  },
  {
    "id": 337,
    "symbol": "MLCF",
    "fullName": "Maple Leaf Cement Factory Limited",
    "icon": "test.svg"
  },
  {
    "id": 338,
    "symbol": "MOHE",
    "fullName": "Mohib Exports Limited(DEF)",
    "icon": "test.svg"
  },
  {
    "id": 339,
    "symbol": "MQTM",
    "fullName": "Maqbool Textile Mills Limited",
    "icon": "test.svg"
  },
  {
    "id": 340,
    "symbol": "MRNS",
    "fullName": "Mehran Sugar Mills Limited",
    "icon": "test.svg"
  },
  {
    "id": 341,
    "symbol": "MSCL",
    "fullName": "Metropolitan Steel Corporation Limited",
    "icon": "test.svg"
  },
  {
    "id": 342,
    "symbol": "MSOT",
    "fullName": "Masood Textile Mills Limited",
    "icon": "test.svg"
  },
  {
    "id": 343,
    "symbol": "MSOTPS",
    "fullName": "Masood Textile (Pref)",
    "icon": "test.svg"
  },
  {
    "id": 344,
    "symbol": "MTL",
    "fullName": "Millat Tractors Limited",
    "icon": "test.svg"
  },
  {
    "id": 345,
    "symbol": "MUBT",
    "fullName": "Mubarak Textile Mills Limited(DEF)",
    "icon": "test.svg"
  },
  {
    "id": 346,
    "symbol": "MUGHAL",
    "fullName": "Mughal Iron & Steel Industries Limited",
    "icon": "test.svg"
  },
  {
    "id": 347,
    "symbol": "MUGHALC",
    "fullName": "Mughal Iron & Steel Industries Ltd(C)",
    "icon": "test.svg"
  },
  {
    "id": 348,
    "symbol": "MUREB",
    "fullName": "Murree Brewery Company Limited",
    "icon": "test.svg"
  },
  {
    "id": 349,
    "symbol": "MWMP",
    "fullName": "Mandviwala Mauser Plastic Industries",
    "icon": "test.svg"
  },
  {
    "id": 350,
    "symbol": "MZNPETF",
    "fullName": "Meezan Pakistan ETF(XD)",
    "icon": "test.svg"
  },
  {
    "id": 351,
    "symbol": "NAFL",
    "fullName": "National Fibres Limited(DEF)",
    "icon": "test.svg"
  },
  {
    "id": 352,
    "symbol": "NAGC",
    "fullName": "Nagina Cotton Mills Limited",
    "icon": "test.svg"
  },
  {
    "id": 353,
    "symbol": "NATF",
    "fullName": "National Foods Limited",
    "icon": "test.svg"
  },
  {
    "id": 354,
    "symbol": "NATM",
    "fullName": "Nadeem Textile Mills Limited",
    "icon": "test.svg"
  },
  {
    "id": 355,
    "symbol": "NBP",
    "fullName": "National Bank of Pakistan",
    "icon": "test.svg"
  },
  {
    "id": 356,
    "symbol": "NBPGETF",
    "fullName": "NBP Pakistan  Growth ETF(XD)",
    "icon": "test.svg"
  },
  {
    "id": 357,
    "symbol": "NCL",
    "fullName": "Nishat Chunian Limited",
    "icon": "test.svg"
  },
  {
    "id": 358,
    "symbol": "NCML",
    "fullName": "Nazir Cotton Mills Limited(DEF)",
    "icon": "test.svg"
  },
  {
    "id": 359,
    "symbol": "NCPL",
    "fullName": "Nishat Chunian Power Limited",
    "icon": "test.svg"
  },
  {
    "id": 360,
    "symbol": "NESTLE",
    "fullName": "Nestle Pakistan Limited",
    "icon": "test.svg"
  },
  {
    "id": 361,
    "symbol": "NETSOL",
    "fullName": "NetSol Technologies Limited",
    "icon": "test.svg"
  },
  {
    "id": 362,
    "symbol": "NEXT",
    "fullName": "Next Capital Limited",
    "icon": "test.svg"
  },
  {
    "id": 363,
    "symbol": "NICL",
    "fullName": "Nimir Industrial Chemicals Limited",
    "icon": "test.svg"
  },
  {
    "id": 364,
    "symbol": "NINA",
    "fullName": "Nina Industries Limited(DEF)",
    "icon": "test.svg"
  },
  {
    "id": 365,
    "symbol": "NITGETF",
    "fullName": "NIT Pakistan Gateway ETF(XD)",
    "icon": "test.svg"
  },
  {
    "id": 366,
    "symbol": "NMFL",
    "fullName": "Nirala MSR Foods Limited(DEF)",
    "icon": "test.svg"
  },
  {
    "id": 367,
    "symbol": "NML",
    "fullName": "Nishat Mills Limited",
    "icon": "test.svg"
  },
  {
    "id": 368,
    "symbol": "NONS",
    "fullName": "Noon Sugar Mills Limited",
    "icon": "test.svg"
  },
  {
    "id": 369,
    "symbol": "NPL",
    "fullName": "Nishat Power Limited",
    "icon": "test.svg"
  },
  {
    "id": 370,
    "symbol": "NRL",
    "fullName": "National Refinery Limited",
    "icon": "test.svg"
  },
  {
    "id": 371,
    "symbol": "NRSL",
    "fullName": "Nimir Resins Limited",
    "icon": "test.svg"
  },
  {
    "id": 372,
    "symbol": "NSRM",
    "fullName": "The National Silk & Rayon Mills Limited",
    "icon": "test.svg"
  },
  {
    "id": 373,
    "symbol": "OBOY",
    "fullName": "Oilboy Energy Limited",
    "icon": "test.svg"
  },
  {
    "id": 374,
    "symbol": "OCTOPUS",
    "fullName": "Octopus Digital Limited",
    "icon": "test.svg"
  },
  {
    "id": 375,
    "symbol": "OGDC",
    "fullName": "Oil & Gas Development Company Limited",
    "icon": "test.svg"
  },
  {
    "id": 376,
    "symbol": "OLPL",
    "fullName": "OLP Financial Services Pakistan Limited",
    "icon": "test.svg"
  },
  {
    "id": 377,
    "symbol": "OLPM",
    "fullName": "OLP Modaraba",
    "icon": "test.svg"
  },
  {
    "id": 378,
    "symbol": "OML",
    "fullName": "Olympia Mills Limited",
    "icon": "test.svg"
  },
  {
    "id": 379,
    "symbol": "ORM",
    "fullName": "Orient Rental Mod",
    "icon": "test.svg"
  },
  {
    "id": 380,
    "symbol": "OTSU",
    "fullName": "Otsuka Pakistan Limited",
    "icon": "test.svg"
  },
  {
    "id": 381,
    "symbol": "PABC",
    "fullName": "Pakistan Aluminium Beverage Cans Limited",
    "icon": "test.svg"
  },
  {
    "id": 382,
    "symbol": "PACE",
    "fullName": "Pace (Pakistan) Limited",
    "icon": "test.svg"
  },
  {
    "id": 383,
    "symbol": "PAEL",
    "fullName": "Pak Elektron Limited",
    "icon": "test.svg"
  },
  {
    "id": 384,
    "symbol": "PAKD",
    "fullName": "Pak Datacom Limited",
    "icon": "test.svg"
  },
  {
    "id": 385,
    "symbol": "PAKL",
    "fullName": "Pak Leather Crafts Limited",
    "icon": "test.svg"
  },
  {
    "id": 386,
    "symbol": "PAKOXY",
    "fullName": "Pakistan Oxygen Limited",
    "icon": "test.svg"
  },
  {
    "id": 387,
    "symbol": "PAKQATAR",
    "fullName": "Pak Qatar Family Takaful Limited",
    "icon": "test.svg"
  },
  {
    "id": 388,
    "symbol": "PAKRI",
    "fullName": "Pakistan Reinsurance Company Limited",
    "icon": "test.svg"
  },
  {
    "id": 389,
    "symbol": "PAKT",
    "fullName": "Pakistan Tobacco Company Limited",
    "icon": "test.svg"
  },
  {
    "id": 390,
    "symbol": "PASL",
    "fullName": "Pervez Ahmed Consultancy Services Ltd.(DEF)",
    "icon": "test.svg"
  },
  {
    "id": 391,
    "symbol": "PASM",
    "fullName": "Paramount Spinning Mills Limited(DEF)",
    "icon": "test.svg"
  },
  {
    "id": 392,
    "symbol": "PCAL",
    "fullName": "Pakistan Cables Limited",
    "icon": "test.svg"
  },
  {
    "id": 393,
    "symbol": "PECO",
    "fullName": "Pakistan Engineering Company Limited(DEF)",
    "icon": "test.svg"
  },
  {
    "id": 394,
    "symbol": "PGLC",
    "fullName": "Pak-Gulf Leasing Company Limited",
    "icon": "test.svg"
  },
  {
    "id": 395,
    "symbol": "PHDL",
    "fullName": "Pakistan Hotels Developers Limited(DEF)",
    "icon": "test.svg"
  },
  {
    "id": 396,
    "symbol": "PIAHCLA",
    "fullName": "PIA Holding Company Limited",
    "icon": "test.svg"
  },
  {
    "id": 397,
    "symbol": "PIAHCLB",
    "fullName": "PIA Holding Company LimitedB",
    "icon": "test.svg"
  },
  {
    "id": 398,
    "symbol": "PIBTL",
    "fullName": "Pakistan International Bulk Terminal",
    "icon": "test.svg"
  },
  {
    "id": 399,
    "symbol": "PICL",
    "fullName": "Pakistan Industrial & Commercial Leasing(DEF)",
    "icon": "test.svg"
  },
  {
    "id": 400,
    "symbol": "PICT",
    "fullName": "Pakistan International Container",
    "icon": "test.svg"
  },
  {
    "id": 401,
    "symbol": "PIL",
    "fullName": "PICIC Insurance Limited(DEF)",
    "icon": "test.svg"
  },
  {
    "id": 402,
    "symbol": "PIM",
    "fullName": "Popular Islamic Modaraba",
    "icon": "test.svg"
  },
  {
    "id": 403,
    "symbol": "PINL",
    "fullName": "Premier Insurance Limited",
    "icon": "test.svg"
  },
  {
    "id": 404,
    "symbol": "PIOC",
    "fullName": "Pioneer Cement Limited",
    "icon": "test.svg"
  },
  {
    "id": 405,
    "symbol": "PKGI",
    "fullName": "The Pakistan General Insurance Co. Ltd.",
    "icon": "test.svg"
  },
  {
    "id": 406,
    "symbol": "PKGP",
    "fullName": "Pakgen Power Limited",
    "icon": "test.svg"
  },
  {
    "id": 407,
    "symbol": "PKGS",
    "fullName": "Packages Limited",
    "icon": "test.svg"
  },
  {
    "id": 408,
    "symbol": "PMRS",
    "fullName": "The Premier Sugar Mills",
    "icon": "test.svg"
  },
  {
    "id": 409,
    "symbol": "PNSC",
    "fullName": "Pakistan National Shipping Corporation",
    "icon": "test.svg"
  },
  {
    "id": 410,
    "symbol": "POL",
    "fullName": "Pakistan Oilfields Limited",
    "icon": "test.svg"
  },
  {
    "id": 411,
    "symbol": "POML",
    "fullName": "Punjab Oil Mills Limited",
    "icon": "test.svg"
  },
  {
    "id": 412,
    "symbol": "POWER",
    "fullName": "Power Cement Limited",
    "icon": "test.svg"
  },
  {
    "id": 413,
    "symbol": "POWERPS",
    "fullName": "Power Cement (Pref)",
    "icon": "test.svg"
  },
  {
    "id": 414,
    "symbol": "PPL",
    "fullName": "Pakistan Petroleum Limited",
    "icon": "test.svg"
  },
  {
    "id": 415,
    "symbol": "PPP",
    "fullName": "Pakistan Paper Products Limited",
    "icon": "test.svg"
  },
  {
    "id": 416,
    "symbol": "PPVC",
    "fullName": "Pakistan PVC Limited(DEF)",
    "icon": "test.svg"
  },
  {
    "id": 417,
    "symbol": "PQGTL",
    "fullName": "Pak Qatar General Takaful Limited",
    "icon": "test.svg"
  },
  {
    "id": 418,
    "symbol": "PREMA",
    "fullName": "At-Tahur Limited",
    "icon": "test.svg"
  },
  {
    "id": 419,
    "symbol": "PRET",
    "fullName": "Premium Textile Mills Limited",
    "icon": "test.svg"
  },
  {
    "id": 420,
    "symbol": "PRIB",
    "fullName": "Prudential Investment Bank Limited(DEF)",
    "icon": "test.svg"
  },
  {
    "id": 421,
    "symbol": "PRIC",
    "fullName": "Progressive Insurance Company Limited(DEF)",
    "icon": "test.svg"
  },
  {
    "id": 422,
    "symbol": "PRL",
    "fullName": "Pakistan Refinery Limited",
    "icon": "test.svg"
  },
  {
    "id": 423,
    "symbol": "PRWM",
    "fullName": "Prosperity Weaving Mills Limited",
    "icon": "test.svg"
  },
  {
    "id": 424,
    "symbol": "PSEL",
    "fullName": "Pakistan Services Limited",
    "icon": "test.svg"
  },
  {
    "id": 425,
    "symbol": "PSO",
    "fullName": "Pakistan State Oil Company Limited",
    "icon": "test.svg"
  },
  {
    "id": 426,
    "symbol": "PSX",
    "fullName": "Pakistan Stock Exchange Limited",
    "icon": "test.svg"
  },
  {
    "id": 427,
    "symbol": "PSYL",
    "fullName": "Pakistan Synthetics Limited",
    "icon": "test.svg"
  },
  {
    "id": 428,
    "symbol": "PTC",
    "fullName": "Pakistan Telecommunication Company Ltd",
    "icon": "test.svg"
  },
  {
    "id": 429,
    "symbol": "PTL",
    "fullName": "Panther Tyres Ltd.",
    "icon": "test.svg"
  },
  {
    "id": 430,
    "symbol": "QTECH",
    "fullName": "Quantum Data Technologies Limited",
    "icon": "test.svg"
  },
  {
    "id": 431,
    "symbol": "QUET",
    "fullName": "Quetta Textile Mills Limited(DEF)",
    "icon": "test.svg"
  },
  {
    "id": 432,
    "symbol": "QUICE",
    "fullName": "Quice Food Industries Limited",
    "icon": "test.svg"
  },
  {
    "id": 433,
    "symbol": "REDCO",
    "fullName": "Redco Textiles Limited",
    "icon": "test.svg"
  },
  {
    "id": 434,
    "symbol": "REGAL",
    "fullName": "Regal Ceramics Limited(DEF)",
    "icon": "test.svg"
  },
  {
    "id": 435,
    "symbol": "REWM",
    "fullName": "Reliance Weaving Mills Limited",
    "icon": "test.svg"
  },
  {
    "id": 436,
    "symbol": "RICL",
    "fullName": "Reliance Insurance Company Limited",
    "icon": "test.svg"
  },
  {
    "id": 437,
    "symbol": "RMPL",
    "fullName": "Rafhan Maize Products Company Limited",
    "icon": "test.svg"
  },
  {
    "id": 438,
    "symbol": "RPL",
    "fullName": "Roshan Packages Limited",
    "icon": "test.svg"
  },
  {
    "id": 439,
    "symbol": "RUBY",
    "fullName": "Ruby Textile Mills Limited(DEF)",
    "icon": "test.svg"
  },
  {
    "id": 440,
    "symbol": "RUPL",
    "fullName": "Rupali Polyester Limited",
    "icon": "test.svg"
  },
  {
    "id": 441,
    "symbol": "SAIF",
    "fullName": "Saif Textile Mills Limited",
    "icon": "test.svg"
  },
  {
    "id": 442,
    "symbol": "SANE",
    "fullName": "Salman Noman Enterprises Limited(DEF)",
    "icon": "test.svg"
  },
  {
    "id": 443,
    "symbol": "SANSM",
    "fullName": "Sanghar Sugar Mills Limited",
    "icon": "test.svg"
  },
  {
    "id": 444,
    "symbol": "SAPT",
    "fullName": "Sapphire Textile Mills Limited",
    "icon": "test.svg"
  },
  {
    "id": 445,
    "symbol": "SARC",
    "fullName": "Sardar Chemical Industries Limited",
    "icon": "test.svg"
  },
  {
    "id": 446,
    "symbol": "SASML",
    "fullName": "Sindh Abadgars Sugar Mills Limited",
    "icon": "test.svg"
  },
  {
    "id": 447,
    "symbol": "SAZEW",
    "fullName": "Sazgar Engineering Works Limited",
    "icon": "test.svg"
  },
  {
    "id": 448,
    "symbol": "SBL",
    "fullName": "Samba Bank Limited",
    "icon": "test.svg"
  },
  {
    "id": 449,
    "symbol": "SCBPL",
    "fullName": "Standard Chartered Bank (Pak) Ltd",
    "icon": "test.svg"
  },
  {
    "id": 450,
    "symbol": "SCHT",
    "fullName": "Schon Textiles Limited(DEF)",
    "icon": "test.svg"
  },
  {
    "id": 451,
    "symbol": "SCL",
    "fullName": "Shield Corporation Limited",
    "icon": "test.svg"
  },
  {
    "id": 452,
    "symbol": "SDOT",
    "fullName": "Sadoon Textile Industries Limited(DEF)",
    "icon": "test.svg"
  },
  {
    "id": 453,
    "symbol": "SEARL",
    "fullName": "The Searle Company Limited",
    "icon": "test.svg"
  },
  {
    "id": 454,
    "symbol": "SEL",
    "fullName": "Sitara Energy Limited",
    "icon": "test.svg"
  },
  {
    "id": 455,
    "symbol": "SEPL",
    "fullName": "Security Papers Limited",
    "icon": "test.svg"
  },
  {
    "id": 456,
    "symbol": "SERT",
    "fullName": "Service Industries Textiles Limited",
    "icon": "test.svg"
  },
  {
    "id": 457,
    "symbol": "SFAT",
    "fullName": "Safa Textiles Limited(DEF)",
    "icon": "test.svg"
  },
  {
    "id": 458,
    "symbol": "SFL",
    "fullName": "Sapphire Fibres Limited",
    "icon": "test.svg"
  },
  {
    "id": 459,
    "symbol": "SGABL",
    "fullName": "SG.Allied Businesses Limited(DEF)",
    "icon": "test.svg"
  },
  {
    "id": 460,
    "symbol": "SGF",
    "fullName": "Service GlobalFootwear Limited",
    "icon": "test.svg"
  },
  {
    "id": 461,
    "symbol": "SGPL",
    "fullName": "S.G. Power Limited",
    "icon": "test.svg"
  },
  {
    "id": 462,
    "symbol": "SHCI",
    "fullName": "Shaffi Chemical Industries Limited(DEF)",
    "icon": "test.svg"
  },
  {
    "id": 463,
    "symbol": "SHCM",
    "fullName": "Shadman Cotton Mills Limited",
    "icon": "test.svg"
  },
  {
    "id": 464,
    "symbol": "SHDT",
    "fullName": "Shadab Textile Mills Limited",
    "icon": "test.svg"
  },
  {
    "id": 465,
    "symbol": "SHEZ",
    "fullName": "Shezan International Limited",
    "icon": "test.svg"
  },
  {
    "id": 466,
    "symbol": "SHFA",
    "fullName": "Shifa International Hospitals Limited",
    "icon": "test.svg"
  },
  {
    "id": 467,
    "symbol": "SHJS",
    "fullName": "Shahtaj Sugar Mills Limited",
    "icon": "test.svg"
  },
  {
    "id": 468,
    "symbol": "SHNI",
    "fullName": "Shaheen Insurance Company Limited",
    "icon": "test.svg"
  },
  {
    "id": 469,
    "symbol": "SHSML",
    "fullName": "Shahmurad Sugar Mills Limited",
    "icon": "test.svg"
  },
  {
    "id": 470,
    "symbol": "SIBL",
    "fullName": "Security Investment Bank Limited",
    "icon": "test.svg"
  },
  {
    "id": 471,
    "symbol": "SIEM",
    "fullName": "Siemens (Pakistan) Engineering",
    "icon": "test.svg"
  },
  {
    "id": 472,
    "symbol": "SINDM",
    "fullName": "Sindh Modaraba",
    "icon": "test.svg"
  },
  {
    "id": 473,
    "symbol": "SITC",
    "fullName": "Sitara Chemical Industries Limited",
    "icon": "test.svg"
  },
  {
    "id": 474,
    "symbol": "SKRS",
    "fullName": "Sakrand Sugar Mills Limited(DEF)",
    "icon": "test.svg"
  },
  {
    "id": 475,
    "symbol": "SLCL",
    "fullName": "Security Leasing Corporation Limited(DEF)",
    "icon": "test.svg"
  },
  {
    "id": 476,
    "symbol": "SLCPA",
    "fullName": "Security Leasing Corp.9.10%(Pref)",
    "icon": "test.svg"
  },
  {
    "id": 477,
    "symbol": "SLGL",
    "fullName": "Secure Logistics-Trax Group Limited",
    "icon": "test.svg"
  },
  {
    "id": 478,
    "symbol": "SLL",
    "fullName": "SME Leasing Limited(DEF)",
    "icon": "test.svg"
  },
  {
    "id": 479,
    "symbol": "SLM",
    "fullName": "Service Long March Tyres Limited",
    "icon": "test.svg"
  },
  {
    "id": 480,
    "symbol": "SLYT",
    "fullName": "Sally Textile Mills Limited(DEF)",
    "icon": "test.svg"
  },
  {
    "id": 481,
    "symbol": "SMCPL",
    "fullName": "Safe Mix Concrete Limited",
    "icon": "test.svg"
  },
  {
    "id": 482,
    "symbol": "SML",
    "fullName": "Shakarganj Limited(DEF)",
    "icon": "test.svg"
  },
  {
    "id": 483,
    "symbol": "SNAI",
    "fullName": "Sana Industries Limited",
    "icon": "test.svg"
  },
  {
    "id": 484,
    "symbol": "SNBL",
    "fullName": "Soneri Bank Limited",
    "icon": "test.svg"
  },
  {
    "id": 485,
    "symbol": "SNGP",
    "fullName": "Sui Northern Gas Pipelines Limited",
    "icon": "test.svg"
  },
  {
    "id": 486,
    "symbol": "SPAC1",
    "fullName": "LSE SPAC-I Limited",
    "icon": "test.svg"
  },
  {
    "id": 487,
    "symbol": "SPCL",
    "fullName": "Saudi Pak Consultancy Company Limited(DEF)",
    "icon": "test.svg"
  },
  {
    "id": 488,
    "symbol": "SPEL",
    "fullName": "SPEL Limited",
    "icon": "test.svg"
  },
  {
    "id": 489,
    "symbol": "SPL",
    "fullName": "Sitara Peroxide Limited(DEF)",
    "icon": "test.svg"
  },
  {
    "id": 490,
    "symbol": "SPSL",
    "fullName": "Sitara Petroleum Service Limited",
    "icon": "test.svg"
  },
  {
    "id": 491,
    "symbol": "SPWL",
    "fullName": "Saif Power Limited",
    "icon": "test.svg"
  },
  {
    "id": 492,
    "symbol": "SRR",
    "fullName": "Signature Residency Reit",
    "icon": "test.svg"
  },
  {
    "id": 493,
    "symbol": "SRVI",
    "fullName": "Service Industries Limited",
    "icon": "test.svg"
  },
  {
    "id": 494,
    "symbol": "SSGC",
    "fullName": "Sui Southern Gas Company Limited",
    "icon": "test.svg"
  },
  {
    "id": 495,
    "symbol": "SSIC",
    "fullName": "Silver Star Insurance Company Limited(DEF)",
    "icon": "test.svg"
  },
  {
    "id": 496,
    "symbol": "SSML",
    "fullName": "Saritow Spinning Mills Limited(DEF)",
    "icon": "test.svg"
  },
  {
    "id": 497,
    "symbol": "SSOM",
    "fullName": "S.S.Oil Mills Limited",
    "icon": "test.svg"
  },
  {
    "id": 498,
    "symbol": "STCL",
    "fullName": "Shabbir Tiles & Ceramics Limited",
    "icon": "test.svg"
  },
  {
    "id": 499,
    "symbol": "STJT",
    "fullName": "Shahtaj Textile Limited",
    "icon": "test.svg"
  },
  {
    "id": 500,
    "symbol": "STL",
    "fullName": "Supernet Technologies Limited",
    "icon": "test.svg"
  },
  {
    "id": 501,
    "symbol": "STML",
    "fullName": "Shams Textile Mills Limited",
    "icon": "test.svg"
  },
  {
    "id": 502,
    "symbol": "STPL",
    "fullName": "Siddiqsons Tin Plate Limited",
    "icon": "test.svg"
  },
  {
    "id": 503,
    "symbol": "STYLERS",
    "fullName": "Stylers International Limited",
    "icon": "test.svg"
  },
  {
    "id": 504,
    "symbol": "SUHJ",
    "fullName": "Suhail Jute Mills Limited(DEF)",
    "icon": "test.svg"
  },
  {
    "id": 505,
    "symbol": "SURAJ",
    "fullName": "Suraj Ghee Industries Limited(DEF)",
    "icon": "test.svg"
  },
  {
    "id": 506,
    "symbol": "SURC",
    "fullName": "Suraj Cotton Mills Limited",
    "icon": "test.svg"
  },
  {
    "id": 507,
    "symbol": "SUTM",
    "fullName": "Sunrays Textile Mills Limited",
    "icon": "test.svg"
  },
  {
    "id": 508,
    "symbol": "SWL",
    "fullName": "Standard Worldwide Limited(DEF)",
    "icon": "test.svg"
  },
  {
    "id": 509,
    "symbol": "SYM",
    "fullName": "Symmetry Group Limited",
    "icon": "test.svg"
  },
  {
    "id": 510,
    "symbol": "SYS",
    "fullName": "Systems Limited",
    "icon": "test.svg"
  },
  {
    "id": 511,
    "symbol": "SZTM",
    "fullName": "Shahzad Textile Mills Limited",
    "icon": "test.svg"
  },
  {
    "id": 512,
    "symbol": "TAJT",
    "fullName": "Taj Textile Mills Limited(DEF)",
    "icon": "test.svg"
  },
  {
    "id": 513,
    "symbol": "TATM",
    "fullName": "Tata Textile Mills Limited",
    "icon": "test.svg"
  },
  {
    "id": 514,
    "symbol": "TBL",
    "fullName": "Treet Battery Limited.",
    "icon": "test.svg"
  },
  {
    "id": 515,
    "symbol": "TCORP",
    "fullName": "Tariq Corporation Limited",
    "icon": "test.svg"
  },
  {
    "id": 516,
    "symbol": "TCORPCPS",
    "fullName": "Tariq Corporation Limited(Pref)",
    "icon": "test.svg"
  },
  {
    "id": 518,
    "symbol": "TELE",
    "fullName": "Telecard Limited",
    "icon": "test.svg"
  },
  {
    "id": 519,
    "symbol": "TGL",
    "fullName": "Tariq Glass Industries Limited",
    "icon": "test.svg"
  },
  {
    "id": 520,
    "symbol": "THALL",
    "fullName": "Thal Limited",
    "icon": "test.svg"
  },
  {
    "id": 521,
    "symbol": "THCCL",
    "fullName": "Thatta Cement Company Limited",
    "icon": "test.svg"
  },
  {
    "id": 522,
    "symbol": "TICL",
    "fullName": "The Thal Industries Corporation Limited",
    "icon": "test.svg"
  },
  {
    "id": 523,
    "symbol": "TOMCL",
    "fullName": "The Organic Meat Company Limited",
    "icon": "test.svg"
  },
  {
    "id": 524,
    "symbol": "TOWL",
    "fullName": "Towellers Limited",
    "icon": "test.svg"
  },
  {
    "id": 525,
    "symbol": "TPL",
    "fullName": "TPL Corp Limited",
    "icon": "test.svg"
  },
  {
    "id": 526,
    "symbol": "TPLI",
    "fullName": "TPL Insurance Limited",
    "icon": "test.svg"
  },
  {
    "id": 527,
    "symbol": "TPLL",
    "fullName": "TPL Life Insurance Limited",
    "icon": "test.svg"
  },
  {
    "id": 528,
    "symbol": "TPLP",
    "fullName": "TPL Properties Limited",
    "icon": "test.svg"
  },
  {
    "id": 529,
    "symbol": "TPLRF1",
    "fullName": "TPL REIT Fund I",
    "icon": "test.svg"
  },
  {
    "id": 530,
    "symbol": "TPLT",
    "fullName": "TPL Trakker Limited",
    "icon": "test.svg"
  },
  {
    "id": 531,
    "symbol": "TREET",
    "fullName": "Treet Corporation Limited",
    "icon": "test.svg"
  },
  {
    "id": 532,
    "symbol": "TRG",
    "fullName": "TRG Pakistan Limited",
    "icon": "test.svg"
  },
  {
    "id": 533,
    "symbol": "TRIBL",
    "fullName": "Trust Investment Bank Limited(DEF)",
    "icon": "test.svg"
  },
  {
    "id": 534,
    "symbol": "TRIPF",
    "fullName": "Tri-Pack Films Limited",
    "icon": "test.svg"
  },
  {
    "id": 535,
    "symbol": "TRSM",
    "fullName": "Trust Modaraba",
    "icon": "test.svg"
  },
  {
    "id": 536,
    "symbol": "TSBL",
    "fullName": "Trust Securities & Brokerage Limited",
    "icon": "test.svg"
  },
  {
    "id": 537,
    "symbol": "TSMF",
    "fullName": "Tri-Star Mutual Fund Limited",
    "icon": "test.svg"
  },
  {
    "id": 538,
    "symbol": "TSML",
    "fullName": "Tandlianwala Sugar Mills Limited",
    "icon": "test.svg"
  },
  {
    "id": 539,
    "symbol": "TSPL",
    "fullName": "Tri-Star Power Limited",
    "icon": "test.svg"
  },
  {
    "id": 540,
    "symbol": "UBDL",
    "fullName": "United Brands Limited",
    "icon": "test.svg"
  },
  {
    "id": 541,
    "symbol": "UBL",
    "fullName": "United Bank Limited",
    "icon": "test.svg"
  },
  {
    "id": 542,
    "symbol": "UBLPETF",
    "fullName": "UBLPakistan Enterprise ETF(XD)",
    "icon": "test.svg"
  },
  {
    "id": 543,
    "symbol": "UCAPM",
    "fullName": "Unicap Modaraba",
    "icon": "test.svg"
  },
  {
    "id": 544,
    "symbol": "UDLI",
    "fullName": "UDL International Limited",
    "icon": "test.svg"
  },
  {
    "id": 545,
    "symbol": "UDPL",
    "fullName": "United Distributors Pakistan Limited",
    "icon": "test.svg"
  },
  {
    "id": 546,
    "symbol": "UNIC",
    "fullName": "The United Insurance Company",
    "icon": "test.svg"
  },
  {
    "id": 547,
    "symbol": "UNITY",
    "fullName": "Unity Foods Limited",
    "icon": "test.svg"
  },
  {
    "id": 548,
    "symbol": "UPFL",
    "fullName": "Unilever Pakistan Foods Limited",
    "icon": "test.svg"
  },
  {
    "id": 549,
    "symbol": "USMT",
    "fullName": "Usman Textile Mills Limited(DEF)",
    "icon": "test.svg"
  },
  {
    "id": 550,
    "symbol": "UVIC",
    "fullName": "The Universal Insurance Company Limited",
    "icon": "test.svg"
  },
  {
    "id": 551,
    "symbol": "WAFI",
    "fullName": "Wafi Energy Pakistan Limited",
    "icon": "test.svg"
  },
  {
    "id": 552,
    "symbol": "WAHDAT",
    "fullName": "Wahdat Poultry Farm Limited",
    "icon": "test.svg"
  },
  {
    "id": 553,
    "symbol": "WAHN",
    "fullName": "Wah Noble Chemicals Limited",
    "icon": "test.svg"
  },
  {
    "id": 554,
    "symbol": "WASL",
    "fullName": "Wasl Mobility Modaraba",
    "icon": "test.svg"
  },
  {
    "id": 555,
    "symbol": "WAVES",
    "fullName": "Waves Corporation Limited",
    "icon": "test.svg"
  },
  {
    "id": 556,
    "symbol": "WAVESAPP",
    "fullName": "Waves Home Appliances Limited",
    "icon": "test.svg"
  },
  {
    "id": 557,
    "symbol": "WTL",
    "fullName": "Worldcall Telecom Limited",
    "icon": "test.svg"
  },
  {
    "id": 558,
    "symbol": "YOUW",
    "fullName": "Yousaf Weaving Mills Limited",
    "icon": "test.svg"
  },
  {
    "id": 559,
    "symbol": "ZAHID",
    "fullName": "Zahidjee Textile Mills Limited",
    "icon": "test.svg"
  },
  {
    "id": 560,
    "symbol": "ZAL",
    "fullName": "Zarea Limited",
    "icon": "test.svg"
  },
  {
    "id": 561,
    "symbol": "ZELP",
    "fullName": "Zeal Pak Cement Factory Limited(DEF)",
    "icon": "test.svg"
  },
  {
    "id": 562,
    "symbol": "ZIL",
    "fullName": "ZIL Limited",
    "icon": "test.svg"
  },
  {
    "id": 563,
    "symbol": "ZTL",
    "fullName": "Zephyr Textiles Limited",
    "icon": "test.svg"
  },
  {
    "id": 564,
    "symbol": "ZUMA",
    "fullName": "Zuma Resources Limited",
    "icon": "test.svg"
  }
]
